[
  {
    "name": {
      "source": "/i18n/StructureViewerConstants",
      "key": "structureViewerPageTitle"
    },
    "pageId": "Awb0ViewerFeature",
    "priority": 1,
    "view": "Awv0StructureViewerPageContainer",
    "visibleWhen": "context.occContext.supportedFeatures.Awb0ViewerFeature && selection.length > 0 && (!context.occContext.supportedFeatures.Awb0PlantCadFeature || context.occContext.supportedFeatures.Awb0PlantCadFeature && ( context.occContext.elementToPCIMap && context.occContext.topElement.modelType.typeHierarchyArray.indexOf( 'Fnd0AppSession' ) === -1) )"
  }
]
