{
    "schemaVersion" : "1.0.0",
    "data":{
        "_provider": {
            "breadcrumbConfig": {
                "type": "search",
                "vm" : "AwClsAdminBreadCrumb"
            },
            "priority": 4,
            "label": {
                "source": "/i18n/ClassificationAdminMessages",
                "key": "propertiesTitle"
            },
            "isXrtApplicable": false,
                "nameToken": "com_siemens_splm_classificationManagerLocation:propertiesSubLocation",
                "clientScopeURI": "Awp0SearchResults",
                "viewModes": {
                    "TreeSummaryView": {
                        "primaryWorkArea": "tree",
                        "secondaryWorkArea": true
                    }
                },
                "defaultDisplayMode": "TreeSummaryView",
                "viewBase": "clsProperties"
        }
    }
}
