{
  "com_siemens_splm_client_logicalobject_configurationLocation": {
    "data": {
      "browserSubTitle": {
        "source": "/i18n/LogicalObjectMessages",
        "key": "configuration"
      },
      "headerTitle": {
        "source": "/i18n/LogicalObjectMessages",
        "key": "configuration"
      },
      "propertyPolicy": "/policies/logicalObjectLocationPropertyPolicy.json"
    },
    "view": "AwSearchLocation",
    "parent": "root"
  },
  "logicalObjects": {
    "data": {
      "priority": 1,
      "label": {
        "source": "/i18n/LogicalObjectMessages",
        "key": "logicalObjects"
      }
    },
    "params": {
      "userId": null,
      "searchCriteria": null,
      "filter": null
    },
    "parent": "com_siemens_splm_client_logicalobject_configurationLocation",
    "selectionMode": "single",
    "view": "LogicalObjectsPage",
    "url": "/logicalObjects"
  }
}
